setup.py
pytsugi/LTIX.py
pytsugi/LTIX_classes.py
pytsugi/__init__.py
pytsugi/oauth.py
pytsugi/outcome_request.py
pytsugi/outcome_response.py
pytsugi/trivialstore.py
pytsugi/utils.py
pytsugi.egg-info/PKG-INFO
pytsugi.egg-info/SOURCES.txt
pytsugi.egg-info/dependency_links.txt
pytsugi.egg-info/top_level.txt